pysunda/__init__.py
pysunda/core.py
pySunda-0.1.0.dist-info/LICENSE
pySunda-0.1.0.dist-info/METADATA
pySunda-0.1.0.dist-info/WHEEL
pySunda-0.1.0.dist-info/top_level.txt
pySunda-0.1.0.dist-info/RECORD
