Metadata-Version: 2.1
Name: pySunda
Version: 0.1.0
Summary: Framework Python pikeun make perintah dina basa Sunda
Home-page: https://github.com/FIZ-Dev/pysunda
Author: Frizqi
Author-email: fadillahfrizqi22@gmail.com
Classifier: Programming Language :: Python :: 3
Classifier: License :: OSI Approved :: MIT License
Classifier: Operating System :: OS Independent
Requires-Python: >=3.6
License-File: LICENSE
